pydopi/GPIO.py
pydopi/I2C.py
pydopi/LED.py
pydopi/WIFI.py
pydopi/__init__.py
pydopi/devmem.py
pydopi/dopi-zero.py
pydopi/version.py
pydopi/config/pin.csv
pydopi-0.0.2.dist-info/.ipynb_checkpoints/PKG-INFO-checkpoint
pydopi-0.0.2.dist-info/.ipynb_checkpoints/SOURCES-checkpoint.txt
pydopi-0.0.2.dist-info/.ipynb_checkpoints/dependency_links-checkpoint.txt
pydopi-0.0.2.dist-info/.ipynb_checkpoints/top_level-checkpoint.txt
pydopi-0.0.2.dist-info/LICENSE
pydopi-0.0.2.dist-info/METADATA
pydopi-0.0.2.dist-info/WHEEL
pydopi-0.0.2.dist-info/top_level.txt
pydopi-0.0.2.dist-info/RECORD
