Metadata-Version: 2.1
Name: pydopi
Version: 0.0.2
Summary: dopi opensource library for IoT
Home-page: https://github.com/cijliu/pydopi
Author: cijliu
Author-email: cijliu@qq.com
License: UNKNOWN
Project-URL: Bug Tracker, https://github.com/cijliu/pydopi/issues
Platform: UNKNOWN
Classifier: Programming Language :: Python :: 3
Classifier: License :: OSI Approved :: MIT License
Classifier: Operating System :: OS Independent
Requires-Python: >=3.6
